{"title":"Body","body":{"content":{"application/json":{"schema":{"required":["name","email","document","documentType"],"type":"object","properties":{"name":{"type":"string","title":"SystemString"},"email":{"type":"string","title":"SystemString"},"document":{"type":"string","title":"SystemString"},"documentType":{"type":"integer","title":"SharedContextEnumsDocumentType"}},"title":"ClientContextCreateCommand"}},"text/json":{"schema":{"required":["name","email","document","documentType"],"type":"object","properties":{"name":{"type":"string","title":"SystemString"},"email":{"type":"string","title":"SystemString"},"document":{"type":"string","title":"SystemString"},"documentType":{"type":"integer","title":"SharedContextEnumsDocumentType"}},"title":"ClientContextCreateCommand"}},"application/*+json":{"schema":{"required":["name","email","document","documentType"],"type":"object","properties":{"name":{"type":"string","title":"SystemString"},"email":{"type":"string","title":"SystemString"},"document":{"type":"string","title":"SystemString"},"documentType":{"type":"integer","title":"SharedContextEnumsDocumentType"}},"title":"ClientContextCreateCommand"}}},"required":true}}